simple_python_utils-1.7.0.dist-info/licenses/LICENSE
simple_utils/__init__.py
simple_utils/core.py
simple_python_utils-1.7.0.dist-info/METADATA
simple_python_utils-1.7.0.dist-info/WHEEL
simple_python_utils-1.7.0.dist-info/top_level.txt
simple_python_utils-1.7.0.dist-info/RECORD
