Metadata-Version: 2.4
Name: simple-python-utils
Version: 1.7.0
Summary: A minimalist Python library with basic utility functions
Home-page: https://github.com/fjmpereira20/simple-python-utils
Author: fjmpereira20
Author-email: fjmpereira20 <fjmpereira20@users.noreply.github.com>
Project-URL: Homepage, https://github.com/fjmpereira20/simple-python-utils
Project-URL: Bug Reports, https://github.com/fjmpereira20/simple-python-utils/issues
Project-URL: Source, https://github.com/fjmpereira20/simple-python-utils
Project-URL: Documentation, https://github.com/fjmpereira20/simple-python-utils#readme
Project-URL: Funding, https://github.com/sponsors/fjmpereira20
Keywords: utilities,python,simple,basic,functions
Classifier: Development Status :: 4 - Beta
Classifier: Intended Audience :: Developers
Classifier: License :: OSI Approved :: MIT License
Classifier: Operating System :: OS Independent
Classifier: Programming Language :: Python :: 3
Classifier: Programming Language :: Python :: 3.9
Classifier: Programming Language :: Python :: 3.10
Classifier: Programming Language :: Python :: 3.11
Classifier: Programming Language :: Python :: 3.12
Classifier: Topic :: Software Development :: Libraries :: Python Modules
Classifier: Topic :: Utilities
Classifier: Typing :: Typed
Requires-Python: >=3.9
License-File: LICENSE
Provides-Extra: dev
Requires-Dist: pytest>=7.0.0; extra == "dev"
Requires-Dist: pytest-cov>=4.0.0; extra == "dev"
Requires-Dist: black>=23.0.0; extra == "dev"
Requires-Dist: isort>=5.12.0; extra == "dev"
Requires-Dist: flake8>=6.0.0; extra == "dev"
Requires-Dist: mypy>=1.0.0; extra == "dev"
Requires-Dist: pre-commit>=3.0.0; extra == "dev"
Requires-Dist: bandit[toml]>=1.7.0; extra == "dev"
Requires-Dist: safety>=2.0.0; extra == "dev"
Requires-Dist: build>=0.10.0; extra == "dev"
Requires-Dist: twine>=4.0.0; extra == "dev"
Provides-Extra: test
Requires-Dist: pytest>=7.0.0; extra == "test"
Requires-Dist: pytest-cov>=4.0.0; extra == "test"
Provides-Extra: qa
Requires-Dist: black>=23.0.0; extra == "qa"
Requires-Dist: isort>=5.12.0; extra == "qa"
Requires-Dist: flake8>=6.0.0; extra == "qa"
Requires-Dist: mypy>=1.0.0; extra == "qa"
Requires-Dist: bandit[toml]>=1.7.0; extra == "qa"
Requires-Dist: safety>=2.0.0; extra == "qa"
Dynamic: author
Dynamic: home-page
Dynamic: license-file
Dynamic: requires-python
